{
    "_links": {
        "self": {
            "href": "http:\/\/www\/node\/5?_format=hal_json"
        },
        "type": {
            "href": "http:\/\/drupal.org\/rest\/type\/node\/page"
        },
        "http:\/\/drupal.org\/rest\/relation\/node\/page\/revision_uid": [
            {
                "href": "http:\/\/www\/user\/1?_format=hal_json"
            }
        ],
        "http:\/\/drupal.org\/rest\/relation\/node\/page\/uid": [
            {
                "href": "http:\/\/www\/user\/1?_format=hal_json",
                "lang": "en"
            }
        ]
    },
    "nid": [
        {
            "value": 5
        }
    ],
    "uuid": [
        {
            "value": "a74fec20-8c51-4cdd-bca6-ae29f76ac8f5"
        }
    ],
    "vid": [
        {
            "value": 5
        }
    ],
    "langcode": [
        {
            "value": "en",
            "lang": "en"
        }
    ],
    "type": [
        {
            "target_id": "page"
        }
    ],
    "revision_timestamp": [
        {
            "value": "2018-06-12T15:23:52+00:00",
            "format": "Y-m-d\\TH:i:sP"
        }
    ],
    "_embedded": {
        "http:\/\/drupal.org\/rest\/relation\/node\/page\/revision_uid": [
            {
                "_links": {
                    "self": {
                        "href": "http:\/\/www\/user\/1?_format=hal_json"
                    },
                    "type": {
                        "href": "http:\/\/drupal.org\/rest\/type\/user\/user"
                    }
                },
                "uuid": [
                    {
                        "value": "e21c92e4-1131-47d8-bba9-5f132ccc5b80"
                    }
                ]
            }
        ],
        "http:\/\/drupal.org\/rest\/relation\/node\/page\/uid": [
            {
                "_links": {
                    "self": {
                        "href": "http:\/\/www\/user\/1?_format=hal_json"
                    },
                    "type": {
                        "href": "http:\/\/drupal.org\/rest\/type\/user\/user"
                    }
                },
                "uuid": [
                    {
                        "value": "e21c92e4-1131-47d8-bba9-5f132ccc5b80"
                    }
                ],
                "lang": "en"
            }
        ]
    },
    "status": [
        {
            "value": false,
            "lang": "en"
        }
    ],
    "title": [
        {
            "value": "aaa",
            "lang": "en"
        }
    ],
    "created": [
        {
            "value": "2018-06-12T15:23:49+00:00",
            "lang": "en",
            "format": "Y-m-d\\TH:i:sP"
        }
    ],
    "changed": [
        {
            "value": "2018-06-12T15:23:52+00:00",
            "lang": "en",
            "format": "Y-m-d\\TH:i:sP"
        }
    ],
    "promote": [
        {
            "value": false
        }
    ],
    "sticky": [
        {
            "value": false,
            "lang": "en"
        }
    ],
    "default_langcode": [
        {
            "value": true,
            "lang": "en"
        }
    ],
    "revision_translation_affected": [
        {
            "value": true,
            "lang": "en"
        }
    ],
    "moderation_state": [
        {
            "value": "draft",
            "lang": "en"
        }
    ],
    "path": [
        {
            "alias": null,
            "pid": null,
            "langcode": "en",
            "lang": "en"
        }
    ],
    "body": [
        {
            "value": "<p>aaa<\/p>\r\n",
            "format": "basic_html",
            "processed": "<p>aaa<\/p>",
            "summary": "",
            "lang": "en"
        }
    ]
}